jcfg/__init__.py
jcfg/error.py
jcfg/json_config.py
jcfg-0.10.2.dist-info/LICENSE
jcfg-0.10.2.dist-info/METADATA
jcfg-0.10.2.dist-info/WHEEL
jcfg-0.10.2.dist-info/top_level.txt
jcfg-0.10.2.dist-info/RECORD
