Metadata-Version: 2.1
Name: jcfg
Version: 0.10.2
Summary: A json-based configuration helper lib for python
Home-page: https://github.com/chkap/jcfg
Author: chkap
Author-email: d47bc0@gmail.com
License: MIT license
Platform: UNKNOWN
Classifier: Programming Language :: Python :: 3
Classifier: License :: OSI Approved :: MIT License
Classifier: Operating System :: OS Independent
Requires-Dist: jstyleson
Requires-Dist: pyyaml
